{"_type":"export","__export_format":4,"__export_date":"2024-03-15T18:43:13.509Z","__export_source":"insomnia.desktop.app:v2022.7.5","resources":[{"_id":"req_643569000f7e46a8a79b33af5749b5a9","parentId":"wrk_92e863e4021049178340991bd9cdc9ef","modified":1710347185718,"created":1674483403831,"url":"127.0.0.1/api/receber nome","name":"exercicio 1","description":"","method":"GET","body":{"mimeType":"application/json","text":"{\n\t\"name\": \"antonio\"\n}"},"parameters":[],"headers":[{"name":"Content-Type","value":"application/json"}],"authentication":{},"metaSortKey":-1674483403831,"isPrivate":false,"settingStoreCookies":true,"settingSendCookies":true,"settingDisableRenderRequestBody":false,"settingEncodeUrl":true,"settingRebuildPath":true,"settingFollowRedirects":"global","_type":"request"},{"_id":"wrk_92e863e4021049178340991bd9cdc9ef","parentId":null,"modified":1674483403822,"created":1674483403822,"name":"New Document","description":"","scope":"design","_type":"workspace"},{"_id":"req_0dcb48cbc694454c99eae49e5ece8016","parentId":"wrk_92e863e4021049178340991bd9cdc9ef","modified":1710347208916,"created":1710337864866,"url":"127.0.0.1/api/frase","name":"exercicio 2","description":"","method":"GET","body":{"mimeType":"application/json","text":"{\n\t\"name\": \"antonio\",\n\t\"year\": \"vou fazer 16 anos\"\n}"},"parameters":[],"headers":[{"name":"Content-Type","value":"application/json"}],"authentication":{},"metaSortKey":-1710337864866,"isPrivate":false,"settingStoreCookies":true,"settingSendCookies":true,"settingDisableRenderRequestBody":false,"settingEncodeUrl":true,"settingRebuildPath":true,"settingFollowRedirects":"global","_type":"request"},{"_id":"req_662fa40538cc46ed80cc1782a480f524","parentId":"wrk_92e863e4021049178340991bd9cdc9ef","modified":1710347215435,"created":1710338275352,"url":"127.0.0.1/api/frase2","name":"exercicio 3","description":"","method":"GET","body":{"mimeType":"application/json","text":"{\n\t\"name\": \"antonio\",\n\t\"year\": \"16\",\n\t\"city\": \"Presidente Epitacio\"\n}"},"parameters":[],"headers":[{"name":"Content-Type","value":"application/json"}],"authentication":{},"metaSortKey":-1710338275352,"isPrivate":false,"settingStoreCookies":true,"settingSendCookies":true,"settingDisableRenderRequestBody":false,"settingEncodeUrl":true,"settingRebuildPath":true,"settingFollowRedirects":"global","_type":"request"},{"_id":"req_b24ad572ef814d15bb25b85c82ac0e86","parentId":"wrk_92e863e4021049178340991bd9cdc9ef","modified":1710347346070,"created":1710338804654,"url":"127.0.0.1/api/conta","name":"exercicio 4","description":"","method":"GET","body":{"mimeType":"application/json","text":"{\n\t\"number\": \"20\",\n\t\"number2\": \"9\"\n}"},"parameters":[],"headers":[{"name":"Content-Type","value":"application/json"}],"authentication":{},"metaSortKey":-1710338804654,"isPrivate":false,"settingStoreCookies":true,"settingSendCookies":true,"settingDisableRenderRequestBody":false,"settingEncodeUrl":true,"settingRebuildPath":true,"settingFollowRedirects":"global","_type":"request"},{"_id":"req_bd132886088c42a7a378d4095e41ebe3","parentId":"wrk_92e863e4021049178340991bd9cdc9ef","modified":1710349295444,"created":1710347349593,"url":"127.0.0.1/api/conta2","name":"exercicio 5","description":"","method":"GET","body":{"mimeType":"application/json","text":"{\n\t\"number\": \"2\",\n\t\"number2\": \"20\",\n\t\"number3\": \"11\"\n}"},"parameters":[],"headers":[{"name":"Content-Type","value":"application/json"}],"authentication":{},"metaSortKey":-1710347349593,"isPrivate":false,"settingStoreCookies":true,"settingSendCookies":true,"settingDisableRenderRequestBody":false,"settingEncodeUrl":true,"settingRebuildPath":true,"settingFollowRedirects":"global","_type":"request"},{"_id":"req_c04c5c2187b646bd9387c19431e0e75d","parentId":"wrk_92e863e4021049178340991bd9cdc9ef","modified":1710349277037,"created":1710347596881,"url":"127.0.0.1/api/conta3","name":"exercicio 6","description":"","method":"GET","body":{"mimeType":"application/json","text":"{\n\t\"number\": \"4\",\n\t\"number2\": \"10\"\n}"},"parameters":[],"headers":[{"name":"Content-Type","value":"application/json"}],"authentication":{},"metaSortKey":-1710347596881,"isPrivate":false,"settingStoreCookies":true,"settingSendCookies":true,"settingDisableRenderRequestBody":false,"settingEncodeUrl":true,"settingRebuildPath":true,"settingFollowRedirects":"global","_type":"request"},{"_id":"req_f0a27b4191274d9580fbed5678c11c87","parentId":"wrk_92e863e4021049178340991bd9cdc9ef","modified":1710349269396,"created":1710347655634,"url":"127.0.0.1/api/conta4","name":"exercicio 7","description":"","method":"GET","body":{"mimeType":"application/json","text":"{\n\t\"number\": \"10\",\n\t\"number2\": \"08\"\n}"},"parameters":[],"headers":[{"name":"Content-Type","value":"application/json"}],"authentication":{},"metaSortKey":-1710347655634,"isPrivate":false,"settingStoreCookies":true,"settingSendCookies":true,"settingDisableRenderRequestBody":false,"settingEncodeUrl":true,"settingRebuildPath":true,"settingFollowRedirects":"global","_type":"request"},{"_id":"req_a6af07cbe0ec48b5a8da9b055cfe28b5","parentId":"wrk_92e863e4021049178340991bd9cdc9ef","modified":1710352902955,"created":1710347815575,"url":"127.0.0.1/api/conta5","name":"exercicio 8","description":"","method":"GET","body":{"mimeType":"application/json","text":"{\n\t\"number\": \"10\",\n\t\"number2\":\"20\",\n\t\"number3\": \"11\",\n\t\"number4\":\"2\",\n\t\"number5\": \"4\"\n}"},"parameters":[],"headers":[{"name":"Content-Type","value":"application/json"}],"authentication":{},"metaSortKey":-1710347890132.5,"isPrivate":false,"settingStoreCookies":true,"settingSendCookies":true,"settingDisableRenderRequestBody":false,"settingEncodeUrl":true,"settingRebuildPath":true,"settingFollowRedirects":"global","_type":"request"},{"_id":"req_b47ededc330143f4ab3dd1277a6dd6b1","parentId":"wrk_92e863e4021049178340991bd9cdc9ef","modified":1710349245010,"created":1710347964690,"url":"127.0.0.1/api/conta6","name":"exercicio 9","description":"","method":"GET","body":{"mimeType":"application/json","text":"{\n\t\"number\": \"8\",\n\t\"number2\": \"15\"\n}"},"parameters":[],"headers":[{"name":"Content-Type","value":"application/json"}],"authentication":{},"metaSortKey":-1710347964690,"isPrivate":false,"settingStoreCookies":true,"settingSendCookies":true,"settingDisableRenderRequestBody":false,"settingEncodeUrl":true,"settingRebuildPath":true,"settingFollowRedirects":"global","_type":"request"},{"_id":"req_b0b570d984944dbc8edab4609771d5ae","parentId":"wrk_92e863e4021049178340991bd9cdc9ef","modified":1710349603380,"created":1710348266963,"url":"127.0.0.1/api/conta7","name":"exercicio 10","description":"","method":"GET","body":{"mimeType":"application/json","text":"{\n\t\"number\": \"18 \"\n}"},"parameters":[],"headers":[{"name":"Content-Type","value":"application/json"}],"authentication":{},"metaSortKey":-1710348266963,"isPrivate":false,"settingStoreCookies":true,"settingSendCookies":true,"settingDisableRenderRequestBody":false,"settingEncodeUrl":true,"settingRebuildPath":true,"settingFollowRedirects":"global","_type":"request"},{"_id":"req_da7f86c2537546038a1f130fd16e96c7","parentId":"wrk_92e863e4021049178340991bd9cdc9ef","modified":1710349192856,"created":1710348322957,"url":"127.0.0.1/api/retangulo","name":"exercicio 11","description":"","method":"GET","body":{"mimeType":"application/json","text":"{\n\t\"base\": \"14\",\n\t\"altura\": \"20\"\n}"},"parameters":[],"headers":[{"name":"Content-Type","value":"application/json"}],"authentication":{},"metaSortKey":-1710348322957,"isPrivate":false,"settingStoreCookies":true,"settingSendCookies":true,"settingDisableRenderRequestBody":false,"settingEncodeUrl":true,"settingRebuildPath":true,"settingFollowRedirects":"global","_type":"request"},{"_id":"req_7950894090ed47a2970d40071f9ee78d","parentId":"wrk_92e863e4021049178340991bd9cdc9ef","modified":1710349155188,"created":1710348382762,"url":"127.0.0.1/api/test","name":"exercicio 12","description":"","method":"GET","body":{"mimeType":"application/json","text":"{\n\t\"valor\":\"100\",\n\t\"percentual\":\"50\"\n}"},"parameters":[],"headers":[{"name":"Content-Type","value":"application/json"}],"authentication":{},"metaSortKey":-1710348382762,"isPrivate":false,"settingStoreCookies":true,"settingSendCookies":true,"settingDisableRenderRequestBody":false,"settingEncodeUrl":true,"settingRebuildPath":true,"settingFollowRedirects":"global","_type":"request"},{"_id":"req_b851df74f99c461d80241136f2dbac12","parentId":"wrk_92e863e4021049178340991bd9cdc9ef","modified":1710353986448,"created":1710348638277,"url":"127.0.0.1/api/salario","name":"exercicio 13","description":"","method":"GET","body":{"mimeType":"application/json","text":"{\n\t\"salario\": \"1000\",\n\t\"percentual\": \"13\"\n}"},"parameters":[],"headers":[{"name":"Content-Type","value":"application/json"}],"authentication":{},"metaSortKey":-1710348638277,"isPrivate":false,"settingStoreCookies":true,"settingSendCookies":true,"settingDisableRenderRequestBody":false,"settingEncodeUrl":true,"settingRebuildPath":true,"settingFollowRedirects":"global","_type":"request"},{"_id":"req_39465145c6b549ac8c64c7f5377e5965","parentId":"wrk_92e863e4021049178340991bd9cdc9ef","modified":1710349117477,"created":1710348784278,"url":"127.0.0.1/api/Pontos","name":"exercicio 14","description":"","method":"GET","body":{"mimeType":"application/json","text":"{\n\t\"salario\": \"1000\"\n}"},"parameters":[],"headers":[{"name":"Content-Type","value":"application/json"}],"authentication":{},"metaSortKey":-1710348784278,"isPrivate":false,"settingStoreCookies":true,"settingSendCookies":true,"settingDisableRenderRequestBody":false,"settingEncodeUrl":true,"settingRebuildPath":true,"settingFollowRedirects":"global","_type":"request"},{"_id":"req_c9d9ded7ae2a4a28a6892a68593f2a77","parentId":"wrk_92e863e4021049178340991bd9cdc9ef","modified":1710349100621,"created":1710348881583,"url":"127.0.0.1/api/comissao","name":"exercicio 15","description":"","method":"GET","body":{"mimeType":"application/json","text":"{\n\t\"valor\":\"20\"\n}"},"parameters":[],"headers":[{"name":"Content-Type","value":"application/json"}],"authentication":{},"metaSortKey":-1710348881583,"isPrivate":false,"settingStoreCookies":true,"settingSendCookies":true,"settingDisableRenderRequestBody":false,"settingEncodeUrl":true,"settingRebuildPath":true,"settingFollowRedirects":"global","_type":"request"},{"_id":"req_47c5313408f4461985a2d8ac769bc721","parentId":"wrk_92e863e4021049178340991bd9cdc9ef","modified":1710349092807,"created":1710348981616,"url":"127.0.0.1/api/hora","name":"exercicio 16","description":"","method":"GET","body":{"mimeType":"application/json","text":"{\n\t\"dias\": \"10\"\n}"},"parameters":[],"headers":[{"name":"Content-Type","value":"application/json"}],"authentication":{},"metaSortKey":-1710348981616,"isPrivate":false,"settingStoreCookies":true,"settingSendCookies":true,"settingDisableRenderRequestBody":false,"settingEncodeUrl":true,"settingRebuildPath":true,"settingFollowRedirects":"global","_type":"request"},{"_id":"req_e302aaf799224ee48eaa7157bbb2e891","parentId":"wrk_92e863e4021049178340991bd9cdc9ef","modified":1710349085449,"created":1710349027764,"url":"127.0.0.1/api/produto","name":"exercicio 17","description":"","method":"GET","body":{"mimeType":"application/json","text":"{\n\t\"produto\": \"5\",\n\t\"quantidade\": \"20\"\n}"},"parameters":[],"headers":[{"name":"Content-Type","value":"application/json"}],"authentication":{},"metaSortKey":-1710349027764,"isPrivate":false,"settingStoreCookies":true,"settingSendCookies":true,"settingDisableRenderRequestBody":false,"settingEncodeUrl":true,"settingRebuildPath":true,"settingFollowRedirects":"global","_type":"request"},{"_id":"req_a6b3409cfd53450d9a841d0ff2a1198c","parentId":"wrk_92e863e4021049178340991bd9cdc9ef","modified":1710527800896,"created":1710527174266,"url":"127.0.0.1/api/exemplo condicao","name":"if exemplo","description":"","method":"GET","body":{"mimeType":"application/json","text":"{\n\t\"idade\": \"100\"\n}"},"parameters":[],"headers":[{"name":"Content-Type","value":"application/json"}],"authentication":{},"metaSortKey":-1710527174266,"isPrivate":false,"settingStoreCookies":true,"settingSendCookies":true,"settingDisableRenderRequestBody":false,"settingEncodeUrl":true,"settingRebuildPath":true,"settingFollowRedirects":"global","_type":"request"},{"_id":"env_345c9bd1a2912c8ecdd515437a154274cef216ec","parentId":"wrk_92e863e4021049178340991bd9cdc9ef","modified":1674483403826,"created":1674483403826,"name":"Base Environment","data":{},"dataPropertyOrder":null,"color":null,"isPrivate":false,"metaSortKey":1674483403826,"_type":"environment"},{"_id":"jar_345c9bd1a2912c8ecdd515437a154274cef216ec","parentId":"wrk_92e863e4021049178340991bd9cdc9ef","modified":1674483403827,"created":1674483403827,"name":"Default Jar","cookies":[],"_type":"cookie_jar"},{"_id":"spc_3f78eb2013b94aaf81b3cf226fcc46ae","parentId":"wrk_92e863e4021049178340991bd9cdc9ef","modified":1710337062268,"created":1674483403822,"fileName":"New Document","contents":"","contentType":"yaml","_type":"api_spec"},{"_id":"uts_1380377451c2487d95e3939bbc8a822b","parentId":"wrk_92e863e4021049178340991bd9cdc9ef","modified":1674483403833,"created":1674483403833,"name":"Example Test Suite","_type":"unit_test_suite"}]}